Workbook

Sheet LP Statement
B2: INVESTOR QUARTERLY STATEMENT
B3: Private Markets Fund Administration | Q2 2024
B8: INVESTOR DETAILS
B9: Investor Name | C9: Stichting Pensioenfonds ABN
B10: Investor Type | C10: Pension Fund
B11: Country | C11: Netherlands
B12: Reporting Currency | C12: EUR
B13: KYC Status | C13: Approved ✓
B14: Statement Date | C14: 30 June 2024
B16: PORTFOLIO SUMMARY
B17: Fund | C17: Total Committed ($) | D17: Total Called ($) | E17: Total Distributed ($) | F17: Unfunded ($)
B18: Apex Buyout Fund III | C18: 400000000 | D18: 375932875 | E18: 25000000 | F18: =C18-D18 -> 24067125
B19: Meridian Growth Capital II | C19: 200000000 | D19: 80000000 | E19: 0 | F19: =C19-D19 -> 120000000
B20: TOTAL | C20: =SUM(C18:C19) -> 600000000 | D20: =SUM(D18:D19) -> 455932875 | E20: =SUM(E18:E19) -> 25000000 | F20: =SUM(F18:F19) -> 144067125

Sheet Transaction Detail
B2: TRANSACTION DETAIL — Stichting Pensioenfonds ABN
B3: All transactions from inception through Q2 2024
B5: Date | C5: Fund | D5: Transaction Type | E5: Amount (Fund Base $) | F5: Currency | G5: FX Rate
B6: 31 Mar 2022 | C6: Apex Buyout Fund III | D6: Management Fee | E6: 1937775 | F6: EUR | G6: 1.1073
B7: 01 Apr 2022 | C7: Apex Buyout Fund III | D7: Capital Call | E7: 55340475 | F7: EUR | G7: 1.0541
B8: 30 Jun 2022 | C8: Apex Buyout Fund III | D8: Management Fee | E8: 1834000 | F8: EUR | G8: 1.048
B9: 01 Jul 2022 | C9: Apex Buyout Fund III | D9: Capital Call | E9: 53644950 | F9: EUR | G9: 1.0218
B10: 30 Sep 2022 | C10: Apex Buyout Fund III | D10: Management Fee | E10: 1714300 | F10: EUR | G10: 0.9796
B11: 31 Dec 2022 | C11: Apex Buyout Fund III | D11: Management Fee | E11: 1873375 | F11: EUR | G11: 1.0705
B12: 31 Mar 2023 | C12: Apex Buyout Fund III | D12: Management Fee | E12: 1905925 | F12: EUR | G12: 1.0891
B13: 01 Apr 2023 | C13: Meridian Growth Capital II | D13: Capital Call | E13: 30000000 | F13: EUR | G13: 1
B14: 30 Jun 2023 | C14: Meridian Growth Capital II | D14: Management Fee | E14: 1000000 | F14: EUR | G14: 1
B15: 30 Jun 2023 | C15: Apex Buyout Fund III | D15: Management Fee | E15: 0 | F15: EUR | G15: 1
B16: 01 Jul 2023 | C16: Apex Buyout Fund III | D16: Capital Call | E16: 96328750 | F16: EUR | G16: 1.1009
B17: 01 Sep 2023 | C17: Meridian Growth Capital II | D17: Capital Call | E17: 50000000 | F17: EUR | G17: 1
... B22: 30 Jun 2024 | C22: Apex Buyout Fund III | D22: Distribution | E22: 25000000 | F22: USD | G22: 1
B23: TOTAL CAPITAL CALLED | E23: 455932875

Sheet Fund Performance
B2: FUND PERFORMANCE METRICS — As at Q2 2024
B4: Fund | C4: Total Commitment ($) | D4: Total Called ($) | E4: Total Distributed ($) | F4: DPI
B5: Apex Buyout Fund III | C5: ='LP Statement'!C18 -> 400000000 | D5: 375932875 | E5: 25000000 | F5: 0.066501234
B6: Meridian Growth Capital II | C6: ='LP Statement'!C19 -> 200000000 | D6: 80000000 | E6: 0 | F6: 0
B9: Note: DPI (Distributions to Paid-In) measures cash returned to investors relative to capital called. DPI > 1.0x indicates full return of capital. All figures in USD fund base currency.

Sheet NAV Attribution
B2: NAV ATTRIBUTION — Stichting Pensioenfonds ABN
B3: Quarterly movement in Net Asset Value by fund | Q2 2022 – Q2 2024
B5: Apex Buyout Fund III
B6: Quarter | C6: Opening NAV ($) | D6: Capital Called ($) | E6: Unrealised Gains / (Losses) ($) | F6: Fees & Expenses ($) | G6: Closing NAV ($)
B7: Q2 2022 | C7: 0 | D7: 55340475 | E7: =G7-C7-D7-F7 -> 198431300 | F7: -3771775 | G7: 250000000
B8: Q3 2022 | C8: =G7 -> 250000000 | D8: 53644950 | E8: =G8-C8-D8-F8 -> -59930650 | F8: -1714300 | G8: 242000000
B9: Q4 2022 | C9: =G8 -> 242000000 | D9: 0 | E9: =G9-C9-D9-F9 -> 17921548 | F9: -1921548 | G9: 258000000
B10: Q1 2023 | C10: =G9 -> 258000000 | D10: 0 | E10: =G10-C10-D10-F10 -> 25905925 | F10: -1905925 | G10: 282000000
B11: Q2 2023 | C11: =G10 -> 282000000 | D11: 0 | E11: =G11-C11-D11-F11 -> 316905925 | F11: -1905925 | G11: 597000000
B12: Q3 2023 | C12: =G11 -> 597000000 | D12: 96328750 | E12: =G12-C12-D12-F12 -> -70478475 | F12: -1850275 | G12: 621000000
B13: Q4 2023 | C13: =G12 -> 621000000 | D13: 0 | E13: =G13-C13-D13-F13 -> 38000000 | F13: 0 | G13: 659000000
B14: Q1 2024 | C14: =G13 -> 659000000 | D14: 170618700 | E14: =G14-C14-D14-F14 -> -148730625 | F14: -1888075 | G14: 679000000
B15: Q2 2024 | C15: =G14 -> 679000000 | D15: 0 | E15: =G15-C15-D15-F15 -> 30888075 | F15: -1888075 | G15: 708000000
B18: Meridian Growth Capital II
B19: Quarter | C19: Opening NAV ($) | D19: Capital Called ($) | E19: Unrealised Gains / (Losses) ($) | F19: Fees & Expenses ($) | G19: Closing NAV ($)
B20: Q2 2023 | C20: 0 | D20: 30000000 | E20: =G20-C20-D20-F20 -> 88000000 | F20: -1000000 | G20: 117000000
B21: Q3 2023 | C21: =G20 -> 117000000 | D21: 50000000 | E21: =G21-C21-D21-F21 -> 24000000 | F21: 0 | G21: 191000000
B22: Q4 2023 | C22: =G21 -> 191000000 | D22: 0 | E22: =G22-C22-D22-F22 -> 23000000 | F22: 0 | G22: 214000000
B23: Q1 2024 | C23: =G22 -> 214000000 | D23: 0 | E23: =G23-C23-D23-F23 -> 25000000 | F23: -1000000 | G23: 238000000
B24: Q2 2024 | C24: =G23 -> 238000000 | D24: 0 | E24: =G24-C24-D24-F24 -> 20500000 | F24: -1000000 | G24: 257500000

Sheet Cash Flow Timeline
B2: CASH FLOW TIMELINE — J-Curve Analysis
B3: Cumulative net cash flow from inception | Negative = capital deployed, Positive = net distributions received
B5: Quarter | C5: Capital Called ($) | D5: Distributions ($) | E5: Fees & Expenses ($) | F5: Net Cash Flow ($) | G5: Cumulative Net ($) | H5: J-Curve Status
B6: 2022Q1 | C6: 0 | D6: 0 | E6: =C6-F6 -> 1937775 | F6: -1937775 | G6: =F6 -> -1937775 | H6: =IF(G6<0,"In J-Curve","Above Water") -> In J-Curve
B7: 2022Q2 | C7: -55340475 | D7: 0 | E7: =C7-F7 -> 1834000 | F7: -57174475 | G7: =G6+F7 -> -59112250 | H7: =IF(G7<0,"In J-Curve","Above Water") -> In J-Curve
B8: 2022Q3 | C8: -53644950 | D8: 0 | E8: =C8-F8 -> 1714300 | F8: -55359250 | G8: =G7+F8 -> -114471500 | H8: =IF(G8<0,"In J-Curve","Above Water") -> In J-Curve
B9: 2022Q4 | C9: 0 | D9: 0 | E9: =C9-F9 -> 1873375 | F9: -1873375 | G9: =G8+F9 -> -116344875 | H9: =IF(G9<0,"In J-Curve","Above Water") -> In J-Curve
B10: 2023Q1 | C10: 0 | D10: 0 | E10: =C10-F10 -> 1905925 | F10: -1905925 | G10: =G9+F10 -> -118250800 | H10: =IF(G10<0,"In J-Curve","Above Water") -> In J-Curve
B11: 2023Q2 | C11: -30000000 | D11: 0 | E11: =C11-F11 -> 1000000 | F11: -31000000 | G11: =G10+F11 -> -149250800 | H11: =IF(G11<0,"In J-Curve","Above Water") -> In J-Curve
B12: 2023Q3 | C12: -146328750 | D12: 0 | E12: =C12-F12 -> 1850275 | F12: -148179025 | G12: =G11+F12 -> -297429825 | H12: =IF(G12<0,"In J-Curve","Above Water") -> In J-Curve
B13: 2024Q1 | C13: -170618700 | D13: 0 | E13: =C13-F13 -> 2888075 | F13: -173506775 | G13: =G12+F13 -> -470936600 | H13: =IF(G13<0,"In J-Curve","Above Water") -> In J-Curve
B14: 2024Q2 | C14: 0 | D14: 25000000 | E14: =C14-F14 -> -25000000 | F14: 25000000 | G14: =G13+F14 -> -445936600 | H14: =IF(G14<0,"In J-Curve","Above Water") -> In J-Curve
B15: TOTAL | C15: =SUM(C6:C14) -> -455932875 | D15: =SUM(D6:D14) -> 25000000 | E15: =SUM(E6:E14) -> -9996275 | F15: =SUM(F6:F14) -> -445936600 | G15: =SUM(G6:G14) -> -1773671025
B17: J-Curve Note: Private equity investments typically show negative cumulative cash flows in early years as capital is deployed. Returns materialise as portfolio companies are sold and distributions are made. This investor remains in the J-Curve phase.

Sheet Fee Summary
B2: FEE SUMMARY — Management Fees & Expenses
B3: Fees charged to Stichting Pensioenfonds ABN from inception through Q2 2024
B5: MANAGEMENT FEES BY FUND & PERIOD
B6: Period | C6: Fund | D6: Fee Type | E6: Local Amount | F6: USD Equivalent ($)
B7: Mar 2022 | C7: Apex Buyout Fund III | D7: Management Fee | E7: ='FX Impact Summary'!D7 -> 1750000 | F7: ='FX Impact Summary'!F7 -> 1937775
B8: Jun 2022 | C8: Apex Buyout Fund III | D8: Management Fee | E8: ='FX Impact Summary'!D9 -> 1750000 | F8: ='FX Impact Summary'!F9 -> 1834000
B9: Sep 2022 | C9: Apex Buyout Fund III | D9: Management Fee | E9: ='FX Impact Summary'!D11 -> 1750000 | F9: ='FX Impact Summary'!F11 -> 1714300
B10: Dec 2022 | C10: Apex Buyout Fund III | D10: Management Fee | E10: ='FX Impact Summary'!D12 -> 1750000 | F10: ='FX Impact Summary'!F12 -> 1873375
B11: Dec 2022 | C11: Apex Buyout Fund III | D11: Other Expense | E11: ='FX Impact Summary'!D13 -> 45000 | F11: ='FX Impact Summary'!F13 -> 48172.5
B12: Mar 2023 | C12: Apex Buyout Fund III | D12: Management Fee | E12: ='FX Impact Summary'!D14 -> 1750000 | F12: ='FX Impact Summary'!F14 -> 1905925
B13: Jun 2023 | C13: Meridian Growth Capital II | D13: Management Fee | E13: ='FX Impact Summary'!D16 -> 1000000 | F13: ='FX Impact Summary'!F16 -> 1000000
B14: Jun 2023 | C14: Apex Buyout Fund III | D14: Management Fee | E14: ='Transaction Detail'!E15 -> 0 | F14: ='Transaction Detail'!E15 -> 0
B15: Sep 2023 | C15: Apex Buyout Fund III | D15: Management Fee | E15: ='FX Impact Summary'!D19 -> 1750000 | F15: ='FX Impact Summary'!F19 -> 1850275
B16: Mar 2024 | C16: Meridian Growth Capital II | D16: Management Fee | E16: ='FX Impact Summary'!D21 -> 1000000 | F16: ='FX Impact Summary'!F21 -> 1000000
B17: Mar 2024 | C17: Apex Buyout Fund III | D17: Management Fee | E17: ='FX Impact Summary'!D22 -> 1750000 | F17: ='FX Impact Summary'!F22 -> 1888075
B18: TOTAL FEES PAID | F18: =SUM(F7:F17) -> 15051898
B20: ANNUAL FEE SUMMARY
B21: Year | C21: Total Fees ($) | D21: As % of Called Capital
B22: 2022 | C22: 7407623 | D22: =C22/'LP Statement'!D20 -> 0.016247179
B23: 2023 | C23: 4756200 | D23: =C23/'LP Statement'!D20 -> 0.010431799
B24: 2024 | C24: 2888075 | D24: =C24/'LP Statement'!D20 -> 0.0063344303

Sheet FX Impact Summary
B2: FX IMPACT SUMMARY — EUR/USD Translation
B3: Stichting Pensioenfonds ABN reports in EUR | Fund base currency is USD
B5: TRANSACTION-LEVEL FX IMPACT
B6: Date | C6: Transaction Type | D6: Local Amount (EUR) | E6: FX Rate Applied | F6: USD Equivalent ($) | G6: Rate vs Current ($)
B7: 31 Mar 2022 | C7: Management Fee | D7: 1750000 | E7: 1.1073 | F7: =D7*E7 -> 1937775 | G7: =(D7*1.0812)-F7 -> -45675
B8: 01 Apr 2022 | C8: Capital Call | D8: 52500000 | E8: 1.0541 | F8: =D8*E8 -> 55340250 | G8: =(D8*1.0812)-F8 -> 1422750
B9: 30 Jun 2022 | C9: Management Fee | D9: 1750000 | E9: 1.048 | F9: =D9*E9 -> 1834000 | G9: =(D9*1.0812)-F9 -> 58100
B10: 01 Jul 2022 | C10: Capital Call | D10: 52500000 | E10: 1.0218 | F10: =D10*E10 -> 53644500 | G10: =(D10*1.0812)-F10 -> 3118500
B11: 30 Sep 2022 | C11: Management Fee | D11: 1750000 | E11: 0.9796 | F11: =D11*E11 -> 1714300 | G11: =(D11*1.0812)-F11 -> 177800
B12: 31 Dec 2022 | C12: Management Fee | D12: 1750000 | E12: 1.0705 | F12: =D12*E12 -> 1873375 | G12: =(D12*1.0812)-F12 -> 18725
B13: 31 Dec 2022 | C13: Other Expense | D13: 45000 | E13: 1.0705 | F13: =D13*E13 -> 48172.5 | G13: =(D13*1.0812)-F13 -> 481.5
B14: 31 Mar 2023 | C14: Management Fee | D14: 1750000 | E14: 1.0891 | F14: =D14*E14 -> 1905925 | G14: =(D14*1.0812)-F14 -> -13825
B15: 01 Apr 2023 | C15: Capital Call | D15: 30000000 | E15: 1 | F15: =D15*E15 -> 30000000 | G15: =(D15*1.0812)-F15 -> 2436000
B16: 30 Jun 2023 | C16: Management Fee | D16: 1000000 | E16: 1 | F16: =D16*E16 -> 1000000 | G16: =(D16*1.0812)-F16 -> 81200
B17: 01 Jul 2023 | C17: Capital Call | D17: 87500000 | E17: 1.1009 | F17: =D17*E17 -> 96328750 | G17: =(D17*1.0812)-F17 -> -1723750
B18: 01 Sep 2023 | C18: Capital Call | D18: 50000000 | E18: 1 | F18: =D18*E18 -> 50000000 | G18: =(D18*1.0812)-F18 -> 4060000
... B22: 31 Mar 2024 | C22: Management Fee | D22: 1750000 | E22: 1.0789 | F22: =D22*E22 -> 1888075 | G22: =(D22*1.0812)-F22 -> 4025
B23: TOTAL FX IMPACT | F23: 470984773 | G23: =SUM(G7:G22) -> 9339356.5
B25: EUR/USD EXCHANGE RATES — QUARTERLY
B26: Quarter End | C26: EUR/USD Rate | D26: vs Prior Quarter
B27: Jan 2022 | C27: 1.1229 | D27: —
B28: Feb 2022 | C28: 1.1127 | D28: =(C28-C27)/C27 -> -0.0090836228
B29: Mar 2022 | C29: 1.1073 | D29: =(C29-C28)/C28 -> -0.0048530601
B30: Apr 2022 | C30: 1.0541 | D30: =(C30-C29)/C29 -> -0.048044794
B31: May 2022 | C31: 1.0723 | D31: =(C31-C30)/C30 -> 0.017265914
B32: Jun 2022 | C32: 1.048 | D32: =(C32-C31)/C31 -> -0.022661569
B33: Jul 2022 | C33: 1.0218 | D33: =(C33-C32)/C32 -> -0.025
B34: Aug 2022 | C34: 0.9958 | D34: =(C34-C33)/C33 -> -0.025445293
B35: Sep 2022 | C35: 0.9796 | D35: =(C35-C34)/C34 -> -0.016268327
B36: Oct 2022 | C36: 0.9964 | D36: =(C36-C35)/C35 -> 0.017149857
B37: Nov 2022 | C37: 1.0338 | D37: =(C37-C36)/C36 -> 0.037535126
B38: Dec 2022 | C38: 1.0705 | D38: =(C38-C37)/C37 -> 0.035500097
B39: Jan 2023 | C39: 1.0862 | D39: =(C39-C38)/C38 -> 0.014666044
... B58: Sep 2024 | C58: 1.1143 | D58: =(C58-C57)/C57 -> 0.0091468937
